lapgm/__init__.py
lapgm/bias_calc.py
lapgm/cupyx_mvn.py
lapgm/lapgm_estim.py
lapgm/laplacian_routines.py
lapgm/param_setup.py
lapgm/typing_details.py
lapgm-0.1.5.dist-info/LICENSE
lapgm-0.1.5.dist-info/METADATA
lapgm-0.1.5.dist-info/WHEEL
lapgm-0.1.5.dist-info/top_level.txt
lapgm-0.1.5.dist-info/RECORD
