Metadata-Version: 2.1
Name: lapgm
Version: 0.1.5
Summary: A spatially regularized Gaussian mixture model for MR bias field correction and intensity normalization.
Home-page: https://github.com/lucianoAvinas/lapgm
Author: Luciano Vinas
Author-email: lucianovinas@g.ucla.edu
License: MIT
Requires-Python: >=3.10
License-File: LICENSE
Requires-Dist: numpy (>=1.20)
Requires-Dist: scipy
Requires-Dist: scikit-learn
Requires-Dist: matplotlib
Provides-Extra: gpu
Requires-Dist: cupy-cuda11x ; extra == 'gpu'
